pbtoyrobot/__init__.py
pbtoyrobot/__main__.py
pbtoyrobot/commandparser.py
pbtoyrobot/input_output.py
pbtoyrobot/robot.py
pbtoyrobot/robot_state.yaml
pbtoyrobot/robotworld.py
pbtoyrobot/tabletop.py
tests/__init__.py
pbtoyrobot-1.0.10.dist-info/LICENSE
pbtoyrobot-1.0.10.dist-info/METADATA
pbtoyrobot-1.0.10.dist-info/WHEEL
pbtoyrobot-1.0.10.dist-info/entry_points.txt
pbtoyrobot-1.0.10.dist-info/top_level.txt
pbtoyrobot-1.0.10.dist-info/RECORD
