Metadata-Version: 2.1
Name: pbtoyrobot
Version: 1.0.10
Summary: A simple project for a toy robot
Home-page: UNKNOWN
Author: Paolo Benini
License: UNKNOWN
Platform: UNKNOWN
Requires-Dist: pyyaml
